setup.py
pambdas/__init__.py
pambdas/dataframe.py
pambdas/indexers.py
pambdas/other_stuff.py
pambdas/series.py
pambdas.egg-info/PKG-INFO
pambdas.egg-info/SOURCES.txt
pambdas.egg-info/dependency_links.txt
pambdas.egg-info/top_level.txt