Metadata-Version: 1.0
Name: pambdas
Version: 0.0.1
Summary: A pure-Python DataFrame implementation, with a similar API to Pandas.
Home-page: UNKNOWN
Author: Daniel Hitchcock
Author-email: UNKNOWN
License: UNKNOWN
Platform: UNKNOWN
